{
    "date": "2023-05-31T05:08:30.620Z",
    "action": "buy",
    "asset": {
        "chain": "BNB",
        "symbol": "BUSD-BD1",
        "ticker": "BUSD",
        "synth": true
    },
    "amount": "$ 400",
    "assetPrice": 27316.16,
    "result": {
        "hash": "C6FCDC107289B477018920EC87535465631412C7403EE0F8771FB06CBCAA0984",
        "url": "https://viewblock.io/thorchain/tx/C6FCDC107289B477018920EC87535465631412C7403EE0F8771FB06CBCAA0984",
        "waitTimeSeconds": 12
    },
    "rsi": 17.1945
}